sigma/pipelines/crowdstrike_stub/__init__.py
pysigma_pipeline_crowdstrike-2.0.0.dist-info/METADATA
pysigma_pipeline_crowdstrike-2.0.0.dist-info/WHEEL
pysigma_pipeline_crowdstrike-2.0.0.dist-info/RECORD
