Metadata-Version: 2.1
Name: pysigma-pipeline-crowdstrike
Version: 2.0.0
Summary: Placeholder for legacy CrowdStrike pipeline project obsoleted by backend
License: LGPL-2.1-only
Author: Thomas Patzke
Author-email: thomas@patzke.org
Requires-Python: >=3.8,<4.0
Classifier: License :: OSI Approved
Classifier: Programming Language :: Python :: 3
Classifier: Programming Language :: Python :: 3.8
Classifier: Programming Language :: Python :: 3.9
Classifier: Programming Language :: Python :: 3.10
Classifier: Programming Language :: Python :: 3.11
Classifier: Programming Language :: Python :: 3.12
Requires-Dist: pysigma-backend-crowdstrike
